twill/__init__.py
twill/__main__.py
twill/agents.py
twill/browser.py
twill/commands.py
twill/errors.py
twill/fork.py
twill/namespaces.py
twill/parse.py
twill/py.typed
twill/shell.py
twill/unit.py
twill/utils.py
twill/extensions/__init__.py
twill/extensions/argparse.py
twill/extensions/check_links.py
twill/extensions/csv_iterate.py
twill/extensions/dirstack.py
twill/extensions/dns_check.py
twill/extensions/formfill.py
twill/extensions/mailman_sf.py
twill/extensions/match_parse.py
twill/extensions/require.py
twill/extensions/shell_test.py
twill-3.3.1.dist-info/licenses/LICENSE.txt
twill-3.3.1.dist-info/METADATA
twill-3.3.1.dist-info/WHEEL
twill-3.3.1.dist-info/entry_points.txt
twill-3.3.1.dist-info/top_level.txt
twill-3.3.1.dist-info/RECORD
