Metadata-Version: 2.4
Name: twill
Version: 3.3.1
Summary: A web browsing and testing language
Author: C. Titus Brown, Ben R. Taylor, Christoph Zwerschke
Maintainer-email: Christoph Zwerschke <cito@online.de>
License: The MIT License, https://opensource.org/licenses/MIT
Project-URL: Homepage, https://github.com/twill-tools/twill
Project-URL: Issues, https://github.com/twill-tools/twill/issues
Project-URL: Documentation, https://twill-tools.github.io/twill/
Project-URL: Source, https://github.com/twill-tools/twill
Project-URL: ChangeLog, https://twill-tools.github.io/twill/changelog.html
Project-URL: Download, https://pypi.org/project/twill/
Keywords: web,testing,browsing,automation
Classifier: Development Status :: 6 - Mature
Classifier: Environment :: Console
Classifier: Intended Audience :: Developers
Classifier: Intended Audience :: System Administrators
Classifier: License :: OSI Approved :: MIT License
Classifier: Natural Language :: English
Classifier: Operating System :: OS Independent
Classifier: Programming Language :: Python
Classifier: Programming Language :: Python :: 3
Classifier: Programming Language :: Python :: 3.8
Classifier: Programming Language :: Python :: 3.9
Classifier: Programming Language :: Python :: 3.10
Classifier: Programming Language :: Python :: 3.11
Classifier: Programming Language :: Python :: 3.12
Classifier: Programming Language :: Python :: 3.13
Classifier: Programming Language :: Python :: 3.14
Classifier: Programming Language :: Other Scripting Engines
Classifier: Topic :: Internet :: WWW/HTTP
Classifier: Topic :: Software Development :: Testing
Requires-Python: >=3.8
License-File: LICENSE.txt
Requires-Dist: lxml<7,>=6
Requires-Dist: httpx<1,>=0.28.1
Requires-Dist: pyparsing<4,>=3.1
Provides-Extra: docs
Requires-Dist: sphinx<9,>=8.2; extra == "docs"
Requires-Dist: sphinx_rtd_theme<4,>=3; extra == "docs"
Provides-Extra: tidy
Requires-Dist: pytidylib<0.4,>=0.3; extra == "tidy"
Provides-Extra: tests
Requires-Dist: tox<5,>=4; extra == "tests"
Requires-Dist: pytest<9,>=8; extra == "tests"
Requires-Dist: pytidylib<0.4,>=0.3; extra == "tests"
Requires-Dist: flask<4,>=3.0; extra == "tests"
Dynamic: license-file
